setoptconf/__init__.py
setoptconf/config.py
setoptconf/datatype.py
setoptconf/exception.py
setoptconf/manager.py
setoptconf/setting.py
setoptconf/util.py
setoptconf/source/__init__.py
setoptconf/source/base.py
setoptconf/source/commandline.py
setoptconf/source/configfile.py
setoptconf/source/environment.py
setoptconf/source/filebased.py
setoptconf/source/jsonfile.py
setoptconf/source/mapping.py
setoptconf/source/modobj.py
setoptconf/source/yamlfile.py
setoptconf-0.3.0.dist-info/LICENSE
setoptconf-0.3.0.dist-info/METADATA
setoptconf-0.3.0.dist-info/WHEEL
setoptconf-0.3.0.dist-info/top_level.txt
setoptconf-0.3.0.dist-info/RECORD
