Metadata-Version: 2.1
Name: setoptconf
Version: 0.3.0
Summary: A module for retrieving program settings from various sources in a consistant method.
Home-page: https://github.com/jayclassless/setoptconf
Author: Jason Simeone
Author-email: jay@classless.net
License: MIT
Keywords: settings,options,configuration,config,arguments
Platform: UNKNOWN
Classifier: Development Status :: 4 - Beta
Classifier: Intended Audience :: Developers
Classifier: License :: OSI Approved :: MIT License
Classifier: Operating System :: OS Independent
Classifier: Programming Language :: Python :: 3
Classifier: Programming Language :: Python :: 3 :: Only
Classifier: Topic :: Software Development :: Libraries :: Python Modules
Requires-Python: >=3.0
Provides-Extra: yaml
Requires-Dist: pyyaml ; extra == 'yaml'
